{"cameraMode":{"drawMode":0,"name":"Shaded","section":"Shading Mode"},"sceneLighting":true,"audioPlay":false,"sceneViewState":{"showFog":true,"showMaterialUpdate":false,"showSkybox":true,"showFlares":true,"showImageEffects":true,"showParticleSystems":true,"showVisualEffectGraphs":true,"m_FxEnabled":true},"in2DMode":false,"pivot":{"x":4.027428150177002,"y":-2.2472171783447267,"z":8.408671379089356},"rotation":{"x":-0.18564939498901368,"y":-0.16074229776859284,"z":0.030807986855506898,"w":-0.9689231514930725},"size":5.887164115905762,"orthographic":false}